execution_trace/__init__.py
execution_trace/constants.py
execution_trace/record.py
execution_trace/utils.py
execution_trace/viewer/__init__.py
execution_trace/viewer/index.html
execution_trace/viewer/viewer.py
execution_trace/viewer/static/css/codemirror.css
execution_trace/viewer/static/css/foundation.min.css
execution_trace/viewer/static/css/style.css
execution_trace/viewer/static/js/active-line.js
execution_trace/viewer/static/js/codemirror.js
execution_trace/viewer/static/js/foundation.min.js
execution_trace/viewer/static/js/handlebars.min.js
execution_trace/viewer/static/js/jquery.js
execution_trace/viewer/static/js/python.js
execution_trace/viewer/static/js/viewer.js
execution_trace-1.2.0.data/scripts/view_trace
execution_trace-1.2.0.dist-info/METADATA
execution_trace-1.2.0.dist-info/RECORD
execution_trace-1.2.0.dist-info/WHEEL
execution_trace-1.2.0.dist-info/top_level.txt
